{
  "name": "Alibaba VDP",
  "platform": "hackerone",
  "in_scope": [
    "*.1688.com",
    "*.9apps.com",
    "*.alibaba-inc.com",
    "*.alibaba.com",
    "*.alibabagroup.com",
    "*.alibabapictures.com",
    "*.aliexpress.com",
    "*.aligames.com",
    "*.alimama.com",
    "*.alios.cn",
    "*.alisports.com",
    "*.aliyun.com",
    "*.amap.com",
    "*.cainiao.com",
    "*.damai.cn",
    "*.dingtalk.com",
    "*.ele.me",
    "*.fliggy.com",
    "*.shuqi.com",
    "*.shuqireader.com",
    "*.sm.cn",
    "*.taobao.com",
    "*.tmall.com",
    "*.tudou.com",
    "*.uc.cn",
    "*.ucweb.com",
    "*.youku.com",
    "www.lazada.*sixcountry"
  ],
  "out_of_scope": [],
  "url": "https://hackerone.com/alibaba_vdp",
  "synced_at": "2026-03-08T00:14:08.704080"
}